<?xml version="1.0" encoding="utf-8"?>
<TextureAtlas imagePath="bfs.png">
	<!-- Created with Adobe Animate version 22.0.1.105 -->
	<!-- http://www.adobe.com/products/animate.html -->
	<SubTexture name="down0000" x="6" y="1042" width="304" height="461"/>
	<SubTexture name="down0001" x="316" y="1042" width="304" height="461"/>
	<SubTexture name="down0002" x="316" y="1042" width="304" height="461"/>
	<SubTexture name="down0003" x="626" y="1043" width="304" height="461"/>
	<SubTexture name="hey0000" x="2790" y="502" width="305" height="499"/>
	<SubTexture name="hey0001" x="6" y="537" width="305" height="499"/>
	<SubTexture name="hey0002" x="6" y="537" width="305" height="499"/>
	<SubTexture name="hey0003" x="317" y="537" width="305" height="499"/>
	<SubTexture name="idle0000" x="628" y="537" width="303" height="500"/>
	<SubTexture name="idle0001" x="937" y="537" width="303" height="500"/>
	<SubTexture name="idle0002" x="1246" y="537" width="303" height="500"/>
	<SubTexture name="idle0003" x="1555" y="537" width="303" height="500"/>
	<SubTexture name="left0000" x="3165" y="6" width="333" height="486"/>
	<SubTexture name="left0001" x="3504" y="6" width="333" height="486"/>
	<SubTexture name="left0002" x="3504" y="6" width="333" height="486"/>
	<SubTexture name="left0003" x="3165" y="498" width="333" height="486"/>
	<SubTexture name="mdown0000" x="1864" y="994" width="304" height="469"/>
	<SubTexture name="mdown0001" x="2174" y="994" width="304" height="469"/>
	<SubTexture name="mdown0002" x="2174" y="994" width="304" height="469"/>
	<SubTexture name="mdown0003" x="2484" y="1007" width="304" height="469"/>
	<SubTexture name="mleft0000" x="2142" y="6" width="335" height="490"/>
	<SubTexture name="mleft0001" x="2483" y="6" width="335" height="490"/>
	<SubTexture name="mleft0002" x="2483" y="6" width="335" height="490"/>
	<SubTexture name="mleft0003" x="2824" y="6" width="335" height="490"/>
	<SubTexture name="mleft0004" x="2824" y="6" width="335" height="490"/>
	<SubTexture name="mleft0005" x="2824" y="6" width="335" height="490"/>
	<SubTexture name="mright0000" x="3504" y="498" width="318" height="486"/>
	<SubTexture name="mright0001" x="2142" y="502" width="318" height="486"/>
	<SubTexture name="mright0002" x="2142" y="502" width="318" height="486"/>
	<SubTexture name="mright0003" x="2466" y="502" width="318" height="486"/>
	<SubTexture name="mup0000" x="6" y="6" width="352" height="525"/>
	<SubTexture name="mup0001" x="364" y="6" width="352" height="525"/>
	<SubTexture name="mup0002" x="364" y="6" width="352" height="525"/>
	<SubTexture name="mup0003" x="722" y="6" width="352" height="525"/>
	<SubTexture name="right0000" x="3101" y="990" width="304" height="482"/>
	<SubTexture name="right0001" x="3411" y="990" width="304" height="482"/>
	<SubTexture name="right0002" x="3411" y="990" width="304" height="482"/>
	<SubTexture name="right0003" x="3721" y="990" width="304" height="482"/>
	<SubTexture name="up0000" x="1080" y="6" width="348" height="525"/>
	<SubTexture name="up0001" x="1434" y="6" width="348" height="525"/>
	<SubTexture name="up0002" x="1434" y="6" width="348" height="525"/>
	<SubTexture name="up0003" x="1788" y="6" width="348" height="525"/>
</TextureAtlas>
